conjecture/__init__.py
conjecture/base.py
conjecture/general.py
conjecture/mapping.py
conjecture/object.py
conjecture/py.typed
conjecture/rich.py
conjecture/sized.py
conjecture/string.py
conjecture-0.1.0.dist-info/LICENSE
conjecture-0.1.0.dist-info/WHEEL
conjecture-0.1.0.dist-info/METADATA
conjecture-0.1.0.dist-info/RECORD
