Metadata-Version: 2.1
Name: conjecture
Version: 0.1.0
Summary: A pythonic assertion library
Home-page: https://github.com/artisanofcode/python-conjecture
License: MIT
Author: Daniel Knell
Author-email: contact@danielknell.co.uk
Requires-Python: >=3.9,<4.0
Classifier: License :: OSI Approved :: MIT License
Classifier: Programming Language :: Python :: 3
Classifier: Programming Language :: Python :: 3.9
Classifier: Programming Language :: Python :: 3.10
Classifier: Topic :: Software Development :: Libraries
Classifier: Topic :: Software Development :: Testing
Classifier: Topic :: Utilities
Project-URL: Repository, https://github.com/artisanofcode/python-conjecture
